nav_components/__init__.py
nav_components/mapping.cpp
nav_components/mapping.pyx
nav_components/planning.cpp
nav_components/planning.pyx
nav_components/mapping.cpython-38-x86_64-linux-gnu.so
nav_components/planning.cpython-38-x86_64-linux-gnu.so
nav_components/mapping.c
nav_components/planning.c
nav_components-0.1.2.dist-info/WHEEL
nav_components-0.1.2.dist-info/METADATA
nav_components-0.1.2.dist-info/RECORD
