Metadata-Version: 2.1
Name: nav-components
Version: 0.1.2
Summary: 
Author: wwwshwww
Author-email: www.shinderu.www@gmail.com
Requires-Python: >=3.7,<3.11
Classifier: Programming Language :: Python :: 3
Classifier: Programming Language :: Python :: 3.10
Classifier: Programming Language :: Python :: 3.7
Classifier: Programming Language :: Python :: 3.8
Classifier: Programming Language :: Python :: 3.9
Requires-Dist: cython (>=0.29.24,<0.30.0)
Requires-Dist: numpy (>=1.21.2,<2.0.0)
